{
"meta":{"test_sets":[],"test_metrics":[],"learn_metrics":[{"best_value":"Min","name":"RMSE"}],"launch_mode":"Train","parameters":"","iteration_count":500,"learn_sets":["learn"],"name":"experiment"},
"iterations":[
{"learn":[228.6547768],"iteration":0,"passed_time":0.001646,"remaining_time":0.821354},
{"learn":[213.9282474],"iteration":1,"passed_time":0.003330541667,"remaining_time":0.829304875},
{"learn":[200.5593964],"iteration":2,"passed_time":0.004866541667,"remaining_time":0.8062237361},
{"learn":[188.6647979],"iteration":3,"passed_time":0.006386791667,"remaining_time":0.7919621667},
{"learn":[177.2149389],"iteration":4,"passed_time":0.007986375,"remaining_time":0.790651125},
{"learn":[166.7366808],"iteration":5,"passed_time":0.00944425,"remaining_time":0.7775765833},
{"learn":[157.3480348],"iteration":6,"passed_time":0.01087820833,"remaining_time":0.7661366726},
{"learn":[148.5541811],"iteration":7,"passed_time":0.012328875,"remaining_time":0.7582258125},
{"learn":[140.7788216],"iteration":8,"passed_time":0.01389916667,"remaining_time":0.7582767593},
{"learn":[133.40684],"iteration":9,"passed_time":0.01542295833,"remaining_time":0.7557249583},
{"learn":[126.869629],"iteration":10,"passed_time":0.01679170833,"remaining_time":0.7464677614},
{"learn":[120.9068616],"iteration":11,"passed_time":0.01824075,"remaining_time":0.7417905},
{"learn":[115.5669043],"iteration":12,"passed_time":0.01986225,"remaining_time":0.7440704423},
{"learn":[110.7042434],"iteration":13,"passed_time":0.02135570833,"remaining_time":0.7413481607},
{"learn":[106.3836001],"iteration":14,"passed_time":0.02274104167,"remaining_time":0.7352936806},
{"learn":[102.5555589],"iteration":15,"passed_time":0.024330125,"remaining_time":0.7359862812},
{"learn":[99.03446091],"iteration":16,"passed_time":0.02573491667,"remaining_time":0.7311743971},
{"learn":[95.78666739],"iteration":17,"passed_time":0.027362375,"remaining_time":0.7327035972},
{"learn":[93.11823773],"iteration":18,"passed_time":0.02886575,"remaining_time":0.73075925},
{"learn":[90.62497879],"iteration":19,"passed_time":0.030289,"remaining_time":0.726936},
{"learn":[88.43689866],"iteration":20,"passed_time":0.03179795833,"remaining_time":0.7252962877},
{"learn":[86.45370675],"iteration":21,"passed_time":0.03326679167,"remaining_time":0.7227966553},
{"learn":[84.70610242],"iteration":22,"passed_time":0.03475025,"remaining_time":0.7206899674},
{"learn":[83.20590759],"iteration":23,"passed_time":0.036318875,"remaining_time":0.7203243542},
{"learn":[81.87789148],"iteration":24,"passed_time":0.037786375,"remaining_time":0.717941125},
{"learn":[80.68586314],"iteration":25,"passed_time":0.03932291667,"remaining_time":0.7168870192},
{"learn":[79.64571261],"iteration":26,"passed_time":0.04075970833,"remaining_time":0.7140497052},
{"learn":[78.67265246],"iteration":27,"passed_time":0.04233216667,"remaining_time":0.713599381},
{"learn":[77.83449796],"iteration":28,"passed_time":0.04381595833,"remaining_time":0.7116315991},
{"learn":[77.13434623],"iteration":29,"passed_time":0.04534391667,"remaining_time":0.7103880278},
{"learn":[76.47670069],"iteration":30,"passed_time":0.04692529167,"remaining_time":0.7099342513},
{"learn":[75.89206093],"iteration":31,"passed_time":0.04828920833,"remaining_time":0.7062296719},
{"learn":[75.38076523],"iteration":32,"passed_time":0.049685,"remaining_time":0.7031180303},
{"learn":[74.91865959],"iteration":33,"passed_time":0.05122841667,"remaining_time":0.702130652},
{"learn":[74.54012374],"iteration":34,"passed_time":0.05278258333,"remaining_time":0.7012543214},
{"learn":[74.1547312],"iteration":35,"passed_time":0.05422741667,"remaining_time":0.6989311481},
{"learn":[73.80567995],"iteration":36,"passed_time":0.05565620833,"remaining_time":0.6964547151},
{"learn":[73.49031835],"iteration":37,"passed_time":0.05705216667,"remaining_time":0.6936342368},
{"learn":[73.23476227],"iteration":38,"passed_time":0.05849420833,"remaining_time":0.6914315395},
{"learn":[72.97764431],"iteration":39,"passed_time":0.06024229167,"remaining_time":0.6927863542},
{"learn":[72.77684557],"iteration":40,"passed_time":0.06164791667,"remaining_time":0.6901559451},
{"learn":[72.61105136],"iteration":41,"passed_time":0.06304283333,"remaining_time":0.6874670873},
{"learn":[72.45038108],"iteration":42,"passed_time":0.06467220833,"remaining_time":0.6873302141},
{"learn":[72.27820831],"iteration":43,"passed_time":0.06629145833,"remaining_time":0.6870205682},
{"learn":[72.13179238],"iteration":44,"passed_time":0.06772145833,"remaining_time":0.6847391898},
{"learn":[72.00870827],"iteration":45,"passed_time":0.0693625,"remaining_time":0.6845777174},
{"learn":[71.8923],"iteration":46,"passed_time":0.07075,"remaining_time":0.6819095745},
{"learn":[71.77703072],"iteration":47,"passed_time":0.07223966667,"remaining_time":0.6802568611},
{"learn":[71.67119779],"iteration":48,"passed_time":0.07365775,"remaining_time":0.6779519439},
{"learn":[71.56413248],"iteration":49,"passed_time":0.07505558333,"remaining_time":0.67550025},
{"learn":[71.48990958],"iteration":50,"passed_time":0.0765835,"remaining_time":0.6742351275},
{"learn":[71.4094398],"iteration":51,"passed_time":0.07857833333,"remaining_time":0.6769825641},
{"learn":[71.31518373],"iteration":52,"passed_time":0.080104625,"remaining_time":0.6755993844},
{"learn":[71.23589702],"iteration":53,"passed_time":0.08159008333,"remaining_time":0.6738736512},
{"learn":[71.15266336],"iteration":54,"passed_time":0.08309666667,"remaining_time":0.6723275758},
{"learn":[71.08849454],"iteration":55,"passed_time":0.08463454167,"remaining_time":0.6710310089},
{"learn":[70.96654063],"iteration":56,"passed_time":0.08620679167,"remaining_time":0.6699931352},
{"learn":[70.88001766],"iteration":57,"passed_time":0.087614375,"remaining_time":0.6676819612},
{"learn":[70.81828746],"iteration":58,"passed_time":0.08898108333,"remaining_time":0.6650958941},
{"learn":[70.76673482],"iteration":59,"passed_time":0.09040804167,"remaining_time":0.6629923056},
{"learn":[70.68375041],"iteration":60,"passed_time":0.09196879167,"remaining_time":0.661873763},
{"learn":[70.61228427],"iteration":61,"passed_time":0.093398,"remaining_time":0.6598116774},
{"learn":[70.54536409],"iteration":62,"passed_time":0.09477241667,"remaining_time":0.6573896204},
{"learn":[70.49675159],"iteration":63,"passed_time":0.09623183333,"remaining_time":0.6555793646},
{"learn":[70.44764616],"iteration":64,"passed_time":0.09764395833,"remaining_time":0.6534634135},
{"learn":[70.39619922],"iteration":65,"passed_time":0.099027625,"remaining_time":0.6511816553},
{"learn":[70.34781203],"iteration":66,"passed_time":0.1003767917,"remaining_time":0.6487037432},
{"learn":[70.27637933],"iteration":67,"passed_time":0.1018464583,"remaining_time":0.6470245588},
{"learn":[70.19798619],"iteration":68,"passed_time":0.1033218333,"remaining_time":0.6453871039},
{"learn":[70.14247464],"iteration":69,"passed_time":0.104775,"remaining_time":0.6436178571},
{"learn":[70.07296528],"iteration":70,"passed_time":0.10621075,"remaining_time":0.6417522782},
{"learn":[70.01645309],"iteration":71,"passed_time":0.1077165833,"remaining_time":0.6403152454},
{"learn":[69.95922548],"iteration":72,"passed_time":0.1091880417,"remaining_time":0.6386752574},
{"learn":[69.91315206],"iteration":73,"passed_time":0.110535625,"remaining_time":0.6363267061},
{"learn":[69.87192586],"iteration":74,"passed_time":0.11202625,"remaining_time":0.6348154167},
{"learn":[69.82458262],"iteration":75,"passed_time":0.1135779583,"remaining_time":0.6336454518},
{"learn":[69.75448917],"iteration":76,"passed_time":0.1158437917,"remaining_time":0.6363886218},
{"learn":[69.70570786],"iteration":77,"passed_time":0.1172677917,"remaining_time":0.6344488216},
{"learn":[69.6527538],"iteration":78,"passed_time":0.1188550417,"remaining_time":0.6333920575},
{"learn":[69.59261425],"iteration":79,"passed_time":0.1203876667,"remaining_time":0.63203525},
{"learn":[69.55141295],"iteration":80,"passed_time":0.1217675833,"remaining_time":0.6298841656},
{"learn":[69.50221992],"iteration":81,"passed_time":0.1231852917,"remaining_time":0.6279445356},
{"learn":[69.44862868],"iteration":82,"passed_time":0.1246657083,"remaining_time":0.6263325346},
{"learn":[69.40241358],"iteration":83,"passed_time":0.1260570833,"remaining_time":0.6242826984},
{"learn":[69.34685154],"iteration":84,"passed_time":0.12756225,"remaining_time":0.6228039265},
{"learn":[69.30551968],"iteration":85,"passed_time":0.1290182083,"remaining_time":0.6210876541},
{"learn":[69.26625115],"iteration":86,"passed_time":0.1304020417,"remaining_time":0.6190349794},
{"learn":[69.22836657],"iteration":87,"passed_time":0.1318440417,"remaining_time":0.6172698314},
{"learn":[69.19176587],"iteration":88,"passed_time":0.133291375,"remaining_time":0.6155365744},
{"learn":[69.13954732],"iteration":89,"passed_time":0.13493225,"remaining_time":0.6146913611},
{"learn":[69.10609563],"iteration":90,"passed_time":0.1363328333,"remaining_time":0.6127486685},
{"learn":[69.07098938],"iteration":91,"passed_time":0.1378839167,"remaining_time":0.6114851957},
{"learn":[69.03905904],"iteration":92,"passed_time":0.1393084167,"remaining_time":0.6096615654},
{"learn":[69.00271619],"iteration":93,"passed_time":0.1407185,"remaining_time":0.6077841596},
{"learn":[68.95419551],"iteration":94,"passed_time":0.1422077917,"remaining_time":0.6062542697},
{"learn":[68.92114213],"iteration":95,"passed_time":0.1437198333,"remaining_time":0.6048209653},
{"learn":[68.88798486],"iteration":96,"passed_time":0.14523725,"remaining_time":0.6034083686},
{"learn":[68.82907185],"iteration":97,"passed_time":0.1466078333,"remaining_time":0.6013913163},
{"learn":[68.767321],"iteration":98,"passed_time":0.148162125,"remaining_time":0.6001314356},
{"learn":[68.7323771],"iteration":99,"passed_time":0.1495939583,"remaining_time":0.5983758333},
{"learn":[68.70020389],"iteration":100,"passed_time":0.1511900417,"remaining_time":0.5972755111},
{"learn":[68.65539012],"iteration":101,"passed_time":0.1525869167,"remaining_time":0.595388165},
{"learn":[68.57977304],"iteration":102,"passed_time":0.153862375,"remaining_time":0.593042358},
{"learn":[68.54311642],"iteration":103,"passed_time":0.1553912083,"remaining_time":0.5916819087},
{"learn":[68.50319658],"iteration":104,"passed_time":0.1568609167,"remaining_time":0.5900958294},
{"learn":[68.44245859],"iteration":105,"passed_time":0.1583572083,"remaining_time":0.5886107555},
{"learn":[68.40315544],"iteration":106,"passed_time":0.159875875,"remaining_time":0.587207653},
{"learn":[68.37180693],"iteration":107,"passed_time":0.16126825,"remaining_time":0.5853440185},
{"learn":[68.32794341],"iteration":108,"passed_time":0.1627924167,"remaining_time":0.5839617882},
{"learn":[68.28645816],"iteration":109,"passed_time":0.164321875,"remaining_time":0.5825957386},
{"learn":[68.24434013],"iteration":110,"passed_time":0.1657036667,"remaining_time":0.5807092462},
{"learn":[68.19965658],"iteration":111,"passed_time":0.1670985,"remaining_time":0.5788769464},
{"learn":[68.16874077],"iteration":112,"passed_time":0.168495375,"remaining_time":0.5770593816},
{"learn":[68.1244056],"iteration":113,"passed_time":0.1699190833,"remaining_time":0.5753400541},
{"learn":[68.07427064],"iteration":114,"passed_time":0.1715475417,"remaining_time":0.5743113351},
{"learn":[68.04520746],"iteration":115,"passed_time":0.1728942917,"remaining_time":0.5723397241},
{"learn":[68.01150901],"iteration":116,"passed_time":0.1743700417,"remaining_time":0.5708010766},
{"learn":[67.9822739],"iteration":117,"passed_time":0.1758049583,"remaining_time":0.5691313058},
{"learn":[67.94445479],"iteration":118,"passed_time":0.1771745417,"remaining_time":0.5672563057},
{"learn":[67.89533575],"iteration":119,"passed_time":0.1786047917,"remaining_time":0.5655818403},
{"learn":[67.87087268],"iteration":120,"passed_time":0.1799839583,"remaining_time":0.5637514067},
{"learn":[67.83987077],"iteration":121,"passed_time":0.1814576667,"remaining_time":0.5622212951},
{"learn":[67.78853988],"iteration":122,"passed_time":0.1831419583,"remaining_time":0.5613375471},
{"learn":[67.75810365],"iteration":123,"passed_time":0.1845742083,"remaining_time":0.5596766317},
{"learn":[67.7215961],"iteration":124,"passed_time":0.18601175,"remaining_time":0.55803525},
{"learn":[67.67898616],"iteration":125,"passed_time":0.1875202083,"remaining_time":0.5566076025},
{"learn":[67.63874899],"iteration":126,"passed_time":0.1889991667,"remaining_time":0.5550920407},
{"learn":[67.59975365],"iteration":127,"passed_time":0.190493625,"remaining_time":0.5536220977},
{"learn":[67.56382626],"iteration":128,"passed_time":0.1918330417,"remaining_time":0.5517058795},
{"learn":[67.53231964],"iteration":129,"passed_time":0.1932444167,"remaining_time":0.5500033397},
{"learn":[67.4944513],"iteration":130,"passed_time":0.194641625,"remaining_time":0.5482653406},
{"learn":[67.45311363],"iteration":131,"passed_time":0.196143125,"remaining_time":0.5468232576},
{"learn":[67.42641123],"iteration":132,"passed_time":0.1976493333,"remaining_time":0.5453932732},
{"learn":[67.40947227],"iteration":133,"passed_time":0.1991192917,"remaining_time":0.5438631399},
{"learn":[67.36691038],"iteration":134,"passed_time":0.2004763333,"remaining_time":0.5420286049},
{"learn":[67.32722664],"iteration":135,"passed_time":0.2020139167,"remaining_time":0.5406843064},
{"learn":[67.29902967],"iteration":136,"passed_time":0.2035077917,"remaining_time":0.539221375},
{"learn":[67.25914838],"iteration":137,"passed_time":0.2050264167,"remaining_time":0.5378229191},
{"learn":[67.2186338],"iteration":138,"passed_time":0.2064888333,"remaining_time":0.5362767542},
{"learn":[67.18458934],"iteration":139,"passed_time":0.20789525,"remaining_time":0.5345877857},
{"learn":[67.15562271],"iteration":140,"passed_time":0.209254125,"remaining_time":0.5327817793},
{"learn":[67.12206903],"iteration":141,"passed_time":0.210836,"remaining_time":0.5315442817},
{"learn":[67.09988443],"iteration":142,"passed_time":0.212225375,"remaining_time":0.5298213907},
{"learn":[67.06106219],"iteration":143,"passed_time":0.2137338333,"remaining_time":0.5283975324},
{"learn":[67.02303234],"iteration":144,"passed_time":0.2151895,"remaining_time":0.5268432586},
{"learn":[66.99302061],"iteration":145,"passed_time":0.21651025,"remaining_time":0.5249632089},
{"learn":[66.94641236],"iteration":146,"passed_time":0.217959375,"remaining_time":0.5233990434},
{"learn":[66.90495182],"iteration":147,"passed_time":0.2193839167,"remaining_time":0.521777964},
{"learn":[66.86768049],"iteration":148,"passed_time":0.2206668333,"remaining_time":0.519825896},
{"learn":[66.81615459],"iteration":149,"passed_time":0.2220672083,"remaining_time":0.5181568194},
{"learn":[66.78734733],"iteration":150,"passed_time":0.2236505,"remaining_time":0.5169140695},
{"learn":[66.74733657],"iteration":151,"passed_time":0.2251203333,"remaining_time":0.5154070789},
{"learn":[66.71523843],"iteration":152,"passed_time":0.2266324583,"remaining_time":0.5139964905},
{"learn":[66.68546178],"iteration":153,"passed_time":0.2280954583,"remaining_time":0.5124742116},
{"learn":[66.64595282],"iteration":154,"passed_time":0.2294715417,"remaining_time":0.5107592379},
{"learn":[66.60814795],"iteration":155,"passed_time":0.2309070833,"remaining_time":0.5091797222},
{"learn":[66.57133006],"iteration":156,"passed_time":0.232394125,"remaining_time":0.5077145533},
{"learn":[66.52731683],"iteration":157,"passed_time":0.2337867917,"remaining_time":0.5060448275},
{"learn":[66.47945499],"iteration":158,"passed_time":0.2352615417,"remaining_time":0.5045546271},
{"learn":[66.43108622],"iteration":159,"passed_time":0.236876625,"remaining_time":0.5033628281},
{"learn":[66.40792695],"iteration":160,"passed_time":0.238319875,"remaining_time":0.5018039604},
{"learn":[66.37237376],"iteration":161,"passed_time":0.2396940417,"remaining_time":0.5001023832},
{"learn":[66.33153889],"iteration":162,"passed_time":0.24120375,"remaining_time":0.4986850537},
{"learn":[66.30098176],"iteration":163,"passed_time":0.2426680417,"remaining_time":0.4971735488},
{"learn":[66.25758627],"iteration":164,"passed_time":0.24413075,"remaining_time":0.4956594015},
{"learn":[66.21541058],"iteration":165,"passed_time":0.24559275,"remaining_time":0.4941444488},
{"learn":[66.16919827],"iteration":166,"passed_time":0.2469800417,"remaining_time":0.4924811609},
{"learn":[66.13759928],"iteration":167,"passed_time":0.2484909167,"remaining_time":0.4910653829},
{"learn":[66.09489989],"iteration":168,"passed_time":0.2499607917,"remaining_time":0.4895681778},
{"learn":[66.04028118],"iteration":169,"passed_time":0.2513712917,"remaining_time":0.4879560368},
{"learn":[66.01495297],"iteration":170,"passed_time":0.2527904167,"remaining_time":0.4863628484},
{"learn":[65.9849906],"iteration":171,"passed_time":0.25409525,"remaining_time":0.4845537326},
{"learn":[65.938874],"iteration":172,"passed_time":0.255674875,"remaining_time":0.4832698504},
{"learn":[65.90742279],"iteration":173,"passed_time":0.2571865833,"remaining_time":0.4818553228},
{"learn":[65.87766537],"iteration":174,"passed_time":0.2585465,"remaining_time":0.4801577857},
{"learn":[65.83348373],"iteration":175,"passed_time":0.26011,"remaining_time":0.4788388636},
{"learn":[65.80239137],"iteration":176,"passed_time":0.2615257083,"remaining_time":0.477247479},
{"learn":[65.7662295],"iteration":177,"passed_time":0.2629829167,"remaining_time":0.4757331414},
{"learn":[65.72897596],"iteration":178,"passed_time":0.2643365417,"remaining_time":0.4740336865},
{"learn":[65.68820341],"iteration":179,"passed_time":0.2658594583,"remaining_time":0.472639037},
{"learn":[65.65462325],"iteration":180,"passed_time":0.2673009583,"remaining_time":0.4710994791},
{"learn":[65.61784107],"iteration":181,"passed_time":0.2686923333,"remaining_time":0.4694734176},
{"learn":[65.58589342],"iteration":182,"passed_time":0.27015225,"remaining_time":0.4679686516},
{"learn":[65.54472078],"iteration":183,"passed_time":0.2716207917,"remaining_time":0.4664791857},
{"learn":[65.51041084],"iteration":184,"passed_time":0.27310025,"remaining_time":0.4650085338},
{"learn":[65.48460459],"iteration":185,"passed_time":0.2744135417,"remaining_time":0.4632572693},
{"learn":[65.45288818],"iteration":186,"passed_time":0.2759803333,"remaining_time":0.4619349964},
{"learn":[65.41199432],"iteration":187,"passed_time":0.2773997083,"remaining_time":0.4603654734},
{"learn":[65.37998983],"iteration":188,"passed_time":0.2790345833,"remaining_time":0.4591521451},
{"learn":[65.35255915],"iteration":189,"passed_time":0.2802906667,"remaining_time":0.4573163509},
{"learn":[65.32369171],"iteration":190,"passed_time":0.2817360417,"remaining_time":0.4557928632},
{"learn":[65.28386682],"iteration":191,"passed_time":0.2831941667,"remaining_time":0.4542906424},
{"learn":[65.25600401],"iteration":192,"passed_time":0.28472475,"remaining_time":0.452904136},
{"learn":[65.23030478],"iteration":193,"passed_time":0.2860725833,"remaining_time":0.4512278892},
{"learn":[65.20148702],"iteration":194,"passed_time":0.2874543333,"remaining_time":0.4496080598},
{"learn":[65.16834163],"iteration":195,"passed_time":0.2889200417,"remaining_time":0.448120881},
{"learn":[65.13963812],"iteration":196,"passed_time":0.290303375,"remaining_time":0.4465072214},
{"learn":[65.10921828],"iteration":197,"passed_time":0.29234325,"remaining_time":0.4458972803},
{"learn":[65.065333],"iteration":198,"passed_time":0.29375525,"remaining_time":0.4443232676},
{"learn":[65.04355528],"iteration":199,"passed_time":0.295177125,"remaining_time":0.4427656875},
{"learn":[65.01716284],"iteration":200,"passed_time":0.2965516667,"remaining_time":0.4411390464},
{"learn":[64.9921932],"iteration":201,"passed_time":0.29803125,"remaining_time":0.4396698639},
{"learn":[64.96850823],"iteration":202,"passed_time":0.2995783333,"remaining_time":0.438299335},
{"learn":[64.93164709],"iteration":203,"passed_time":0.3010609583,"remaining_time":0.4368335474},
{"learn":[64.90454232],"iteration":204,"passed_time":0.30257275,"remaining_time":0.4354095671},
{"learn":[64.87338464],"iteration":205,"passed_time":0.304154625,"remaining_time":0.4340847561},
{"learn":[64.83880497],"iteration":206,"passed_time":0.3058259583,"remaining_time":0.432884086},
{"learn":[64.81676862],"iteration":207,"passed_time":0.3071785833,"remaining_time":0.4312314728},
{"learn":[64.79283636],"iteration":208,"passed_time":0.3086827917,"remaining_time":0.4297927865},
{"learn":[64.76321274],"iteration":209,"passed_time":0.310104125,"remaining_time":0.4282390298},
{"learn":[64.73637415],"iteration":210,"passed_time":0.3114712083,"remaining_time":0.4266122237},
{"learn":[64.70550735],"iteration":211,"passed_time":0.3129886667,"remaining_time":0.4251921509},
{"learn":[64.68024255],"iteration":212,"passed_time":0.3144760833,"remaining_time":0.4237306851},
{"learn":[64.65004933],"iteration":213,"passed_time":0.3161532917,"remaining_time":0.4225226234},
{"learn":[64.6175525],"iteration":214,"passed_time":0.3177395,"remaining_time":0.4211895698},
{"learn":[64.58951741],"iteration":215,"passed_time":0.319191125,"remaining_time":0.4196772199},
{"learn":[64.56049512],"iteration":216,"passed_time":0.3206640417,"remaining_time":0.4181931972},
{"learn":[64.53223864],"iteration":217,"passed_time":0.3220349583,"remaining_time":0.4165773314},
{"learn":[64.50566262],"iteration":218,"passed_time":0.3235959583,"remaining_time":0.4152075995},
{"learn":[64.47001192],"iteration":219,"passed_time":0.3249500417,"remaining_time":0.4135727803},
{"learn":[64.44837698],"iteration":220,"passed_time":0.3264236667,"remaining_time":0.4120914163},
{"learn":[64.42720154],"iteration":221,"passed_time":0.3279290417,"remaining_time":0.410649881},
{"learn":[64.39972124],"iteration":222,"passed_time":0.3292098333,"remaining_time":0.4089288064},
{"learn":[64.37485169],"iteration":223,"passed_time":0.3305677083,"remaining_time":0.4073066406},
{"learn":[64.34248824],"iteration":224,"passed_time":0.3319475,"remaining_time":0.4057136111},
{"learn":[64.30807707],"iteration":225,"passed_time":0.3334733333,"remaining_time":0.404299528},
{"learn":[64.27874821],"iteration":226,"passed_time":0.3350222917,"remaining_time":0.4029122715},
{"learn":[64.23816529],"iteration":227,"passed_time":0.3365672083,"remaining_time":0.4015187749},
{"learn":[64.21411921],"iteration":228,"passed_time":0.3380811667,"remaining_time":0.4000873195},
{"learn":[64.17783916],"iteration":229,"passed_time":0.3395932917,"remaining_time":0.3986529946},
{"learn":[64.15915015],"iteration":230,"passed_time":0.34106175,"remaining_time":0.3971671461},
{"learn":[64.1370558],"iteration":231,"passed_time":0.342376625,"remaining_time":0.3955040323},
{"learn":[64.11301738],"iteration":232,"passed_time":0.343672125,"remaining_time":0.3938217055},
{"learn":[64.07475397],"iteration":233,"passed_time":0.3450496667,"remaining_time":0.3922359459},
{"learn":[64.05192412],"iteration":234,"passed_time":0.3464289583,"remaining_time":0.3906539317},
{"learn":[64.02274299],"iteration":235,"passed_time":0.3479072917,"remaining_time":0.389184428},
{"learn":[63.99872988],"iteration":236,"passed_time":0.349411125,"remaining_time":0.3877431472},
{"learn":[63.97173653],"iteration":237,"passed_time":0.3507270833,"remaining_time":0.3860945203},
{"learn":[63.95425247],"iteration":238,"passed_time":0.3520866667,"remaining_time":0.384496318},
{"learn":[63.92933237],"iteration":239,"passed_time":0.3534102917,"remaining_time":0.3828611493},
{"learn":[63.90392525],"iteration":240,"passed_time":0.35494575,"remaining_time":0.381456221},
{"learn":[63.86577042],"iteration":241,"passed_time":0.3564283333,"remaining_time":0.379993843},
{"learn":[63.83136503],"iteration":242,"passed_time":0.3577917917,"remaining_time":0.3784053105},
{"learn":[63.81010534],"iteration":243,"passed_time":0.359147875,"remaining_time":0.3768108852},
{"learn":[63.78423827],"iteration":244,"passed_time":0.3605705,"remaining_time":0.3752876633},
{"learn":[63.758152],"iteration":245,"passed_time":0.3620632083,"remaining_time":0.3738376216},
{"learn":[63.72747949],"iteration":246,"passed_time":0.363668,"remaining_time":0.3725020405},
{"learn":[63.7082697],"iteration":247,"passed_time":0.36523175,"remaining_time":0.3711225847},
{"learn":[63.68937834],"iteration":248,"passed_time":0.3665027917,"remaining_time":0.3694465892},
{"learn":[63.66845778],"iteration":249,"passed_time":0.3680315833,"remaining_time":0.3680315833},
{"learn":[63.64609193],"iteration":250,"passed_time":0.369360125,"remaining_time":0.3664170164},
{"learn":[63.62128616],"iteration":251,"passed_time":0.37071475,"remaining_time":0.3648303889},
{"learn":[63.60818601],"iteration":252,"passed_time":0.3727565833,"remaining_time":0.3639165063},
{"learn":[63.58134209],"iteration":253,"passed_time":0.3743297083,"remaining_time":0.3625397963},
{"learn":[63.56083233],"iteration":254,"passed_time":0.3757592083,"remaining_time":0.3610235531},
{"learn":[63.52581471],"iteration":255,"passed_time":0.3771735,"remaining_time":0.3594934922},
{"learn":[63.49320397],"iteration":256,"passed_time":0.3785313333,"remaining_time":0.3579109494},
{"learn":[63.45507513],"iteration":257,"passed_time":0.3801687083,"remaining_time":0.3565923543},
{"learn":[63.43008048],"iteration":258,"passed_time":0.38163725,"remaining_time":0.3551141979},
{"learn":[63.40599166],"iteration":259,"passed_time":0.3830166667,"remaining_time":0.3535538462},
{"learn":[63.39124201],"iteration":260,"passed_time":0.38448275,"remaining_time":0.3520742423},
{"learn":[63.3648921],"iteration":261,"passed_time":0.3859539167,"remaining_time":0.3505993594},
{"learn":[63.33227768],"iteration":262,"passed_time":0.3874210417,"remaining_time":0.3491208626},
{"learn":[63.31710246],"iteration":263,"passed_time":0.388759125,"remaining_time":0.3475270966},
{"learn":[63.29605743],"iteration":264,"passed_time":0.3901624583,"remaining_time":0.3459931234},
{"learn":[63.26786656],"iteration":265,"passed_time":0.3915219167,"remaining_time":0.3444215357},
{"learn":[63.23624738],"iteration":266,"passed_time":0.3928872083,"remaining_time":0.3428566275},
{"learn":[63.21137292],"iteration":267,"passed_time":0.39442075,"remaining_time":0.3414388582},
{"learn":[63.18937418],"iteration":268,"passed_time":0.3959164583,"remaining_time":0.3399877393},
{"learn":[63.17302963],"iteration":269,"passed_time":0.3974582083,"remaining_time":0.3385755108},
{"learn":[63.15427499],"iteration":270,"passed_time":0.398806125,"remaining_time":0.3369985337},
{"learn":[63.127547],"iteration":271,"passed_time":0.400214,"remaining_time":0.3354735},
{"learn":[63.09943156],"iteration":272,"passed_time":0.4016795417,"remaining_time":0.3339972746},
{"learn":[63.07413358],"iteration":273,"passed_time":0.4031929167,"remaining_time":0.3325605809},
{"learn":[63.04333957],"iteration":274,"passed_time":0.4045179583,"remaining_time":0.3309692386},
{"learn":[63.01720625],"iteration":275,"passed_time":0.4058704583,"remaining_time":0.3294021111},
{"learn":[62.99935281],"iteration":276,"passed_time":0.4074555833,"remaining_time":0.328023809},
{"learn":[62.97535638],"iteration":277,"passed_time":0.409007,"remaining_time":0.3266171007},
{"learn":[62.94499672],"iteration":278,"passed_time":0.4104797083,"remaining_time":0.3251470091},
{"learn":[62.92348431],"iteration":279,"passed_time":0.411980875,"remaining_time":0.3236992589},
{"learn":[62.90152856],"iteration":280,"passed_time":0.413587375,"remaining_time":0.3223332211},
{"learn":[62.87787628],"iteration":281,"passed_time":0.415265375,"remaining_time":0.3210207509},
{"learn":[62.86026832],"iteration":282,"passed_time":0.416632375,"remaining_time":0.3194672275},
{"learn":[62.83802929],"iteration":283,"passed_time":0.4179280417,"remaining_time":0.3178607641},
{"learn":[62.80772621],"iteration":284,"passed_time":0.4196071667,"remaining_time":0.3165457573},
{"learn":[62.7822887],"iteration":285,"passed_time":0.421245,"remaining_time":0.3151973077},
{"learn":[62.74992383],"iteration":286,"passed_time":0.422691625,"remaining_time":0.3137049342},
{"learn":[62.7307309],"iteration":287,"passed_time":0.4239924583,"remaining_time":0.3121055596},
{"learn":[62.71786246],"iteration":288,"passed_time":0.42541925,"remaining_time":0.3106002137},
{"learn":[62.69131907],"iteration":289,"passed_time":0.426858125,"remaining_time":0.3091041595},
{"learn":[62.66839096],"iteration":290,"passed_time":0.428399625,"remaining_time":0.3076822049},
{"learn":[62.64026203],"iteration":291,"passed_time":0.429976,"remaining_time":0.306284274},
{"learn":[62.61771426],"iteration":292,"passed_time":0.4314083333,"remaining_time":0.3047833618},
{"learn":[62.59006732],"iteration":293,"passed_time":0.4329222083,"remaining_time":0.3033400507},
{"learn":[62.56885855],"iteration":294,"passed_time":0.4345025833,"remaining_time":0.3019424732},
{"learn":[62.55359259],"iteration":295,"passed_time":0.4359984583,"remaining_time":0.300485424},
{"learn":[62.53112409],"iteration":296,"passed_time":0.4374677917,"remaining_time":0.2990099721},
{"learn":[62.50148663],"iteration":297,"passed_time":0.438908125,"remaining_time":0.2975149035},
{"learn":[62.48451627],"iteration":298,"passed_time":0.440266875,"remaining_time":0.2959653574},
{"learn":[62.45902744],"iteration":299,"passed_time":0.4417200833,"remaining_time":0.2944800556},
{"learn":[62.43240027],"iteration":300,"passed_time":0.4432312083,"remaining_time":0.2930332573},
{"learn":[62.41219715],"iteration":301,"passed_time":0.4447379583,"remaining_time":0.2915831647},
{"learn":[62.39553924],"iteration":302,"passed_time":0.4462998333,"remaining_time":0.2901685385},
{"learn":[62.37337283],"iteration":303,"passed_time":0.44775375,"remaining_time":0.2886833388},
{"learn":[62.34746768],"iteration":304,"passed_time":0.44920075,"remaining_time":0.2871939221},
{"learn":[62.32088206],"iteration":305,"passed_time":0.45069175,"remaining_time":0.2857326781},
{"learn":[62.29555577],"iteration":306,"passed_time":0.4521930417,"remaining_time":0.2842777102},
{"learn":[62.26645578],"iteration":307,"passed_time":0.4536887083,"remaining_time":0.2828189351},
{"learn":[62.24163965],"iteration":308,"passed_time":0.4550324583,"remaining_time":0.2812660179},
{"learn":[62.2202102],"iteration":309,"passed_time":0.4565124583,"remaining_time":0.2797979583},
{"learn":[62.19864736],"iteration":310,"passed_time":0.4578967917,"remaining_time":0.2782716837},
{"learn":[62.173263],"iteration":311,"passed_time":0.4593630417,"remaining_time":0.276795679},
{"learn":[62.15891023],"iteration":312,"passed_time":0.4610411667,"remaining_time":0.27544632},
{"learn":[62.13801643],"iteration":313,"passed_time":0.4625255417,"remaining_time":0.2739800979},
{"learn":[62.11595343],"iteration":314,"passed_time":0.4640914583,"remaining_time":0.2725616501},
{"learn":[62.10038387],"iteration":315,"passed_time":0.4655052917,"remaining_time":0.2710537141},
{"learn":[62.0742169],"iteration":316,"passed_time":0.4670456667,"remaining_time":0.2696194227},
{"learn":[62.05931351],"iteration":317,"passed_time":0.4686515,"remaining_time":0.2682219277},
{"learn":[62.03372754],"iteration":318,"passed_time":0.4703959167,"remaining_time":0.2669017584},
{"learn":[62.01554063],"iteration":319,"passed_time":0.4719970833,"remaining_time":0.2654983594},
{"learn":[61.9967484],"iteration":320,"passed_time":0.4734762083,"remaining_time":0.2640256738},
{"learn":[61.96990957],"iteration":321,"passed_time":0.4751187917,"remaining_time":0.2626433072},
{"learn":[61.94354411],"iteration":322,"passed_time":0.4766883333,"remaining_time":0.2612193034},
{"learn":[61.9203345],"iteration":323,"passed_time":0.4784607083,"remaining_time":0.2599045823},
{"learn":[61.90291812],"iteration":324,"passed_time":0.479995375,"remaining_time":0.2584590481},
{"learn":[61.88179013],"iteration":325,"passed_time":0.4814085,"remaining_time":0.2569480951},
{"learn":[61.86119404],"iteration":326,"passed_time":0.482951625,"remaining_time":0.2555065172},
{"learn":[61.8449635],"iteration":327,"passed_time":0.4844953333,"remaining_time":0.254064626},
{"learn":[61.81621434],"iteration":328,"passed_time":0.4862550417,"remaining_time":0.2527343834},
{"learn":[61.78781783],"iteration":329,"passed_time":0.487721875,"remaining_time":0.2512506629},
{"learn":[61.75697434],"iteration":330,"passed_time":0.4891267083,"remaining_time":0.2497353888},
{"learn":[61.73275639],"iteration":331,"passed_time":0.4904905833,"remaining_time":0.2482000542},
{"learn":[61.70993658],"iteration":332,"passed_time":0.4919159583,"remaining_time":0.2466965917},
{"learn":[61.68684969],"iteration":333,"passed_time":0.4934067917,"remaining_time":0.24522613},
{"learn":[61.665242],"iteration":334,"passed_time":0.4947949583,"remaining_time":0.2437049795},
{"learn":[61.6429814],"iteration":335,"passed_time":0.496317375,"remaining_time":0.2422501473},
{"learn":[61.62102081],"iteration":336,"passed_time":0.4977848333,"remaining_time":0.2407683318},
{"learn":[61.6014552],"iteration":337,"passed_time":0.4991520417,"remaining_time":0.2392385525},
{"learn":[61.5718279],"iteration":338,"passed_time":0.5006751667,"remaining_time":0.2377837812},
{"learn":[61.55053129],"iteration":339,"passed_time":0.502086625,"remaining_time":0.2362760588},
{"learn":[61.53071175],"iteration":340,"passed_time":0.503469625,"remaining_time":0.2347556316},
{"learn":[61.51166657],"iteration":341,"passed_time":0.5048835,"remaining_time":0.2332502719},
{"learn":[61.49440417],"iteration":342,"passed_time":0.506507625,"remaining_time":0.2318416826},
{"learn":[61.47573742],"iteration":343,"passed_time":0.5080864167,"remaining_time":0.230411282},
{"learn":[61.45421842],"iteration":344,"passed_time":0.509543125,"remaining_time":0.2289251721},
{"learn":[61.4312459],"iteration":345,"passed_time":0.5111185417,"remaining_time":0.2274920677},
{"learn":[61.4148959],"iteration":346,"passed_time":0.5125927917,"remaining_time":0.2260135364},
{"learn":[61.40076438],"iteration":347,"passed_time":0.5140438333,"remaining_time":0.2245248927},
{"learn":[61.37057613],"iteration":348,"passed_time":0.515495875,"remaining_time":0.2230368972},
{"learn":[61.35037853],"iteration":349,"passed_time":0.5169231667,"remaining_time":0.2215385},
{"learn":[61.32885142],"iteration":350,"passed_time":0.518518125,"remaining_time":0.2201116827},
{"learn":[61.30009312],"iteration":351,"passed_time":0.520001375,"remaining_time":0.2186369418},
{"learn":[61.27647816],"iteration":352,"passed_time":0.5215681667,"remaining_time":0.2171969419},
{"learn":[61.26496052],"iteration":353,"passed_time":0.5232357917,"remaining_time":0.2157978124},
{"learn":[61.25496743],"iteration":354,"passed_time":0.52467025,"remaining_time":0.2143019331},
{"learn":[61.22940965],"iteration":355,"passed_time":0.5263409583,"remaining_time":0.2129019607},
{"learn":[61.21749326],"iteration":356,"passed_time":0.527971875,"remaining_time":0.2114845326},
{"learn":[61.18811487],"iteration":357,"passed_time":0.5295777083,"remaining_time":0.2100559625},
{"learn":[61.16447541],"iteration":358,"passed_time":0.5310625,"remaining_time":0.2085788649},
{"learn":[61.14688608],"iteration":359,"passed_time":0.5326294167,"remaining_time":0.207133662},
{"learn":[61.13430845],"iteration":360,"passed_time":0.5340329167,"remaining_time":0.2056248627},
{"learn":[61.10342928],"iteration":361,"passed_time":0.5354535,"remaining_time":0.2041231575},
{"learn":[61.08548268],"iteration":362,"passed_time":0.5369013333,"remaining_time":0.2026321837},
{"learn":[61.06919192],"iteration":363,"passed_time":0.53895925,"remaining_time":0.2013693901},
{"learn":[61.04898554],"iteration":364,"passed_time":0.54064475,"remaining_time":0.1999644966},
{"learn":[61.03244461],"iteration":365,"passed_time":0.5420835,"remaining_time":0.1984677295},
{"learn":[61.00957387],"iteration":366,"passed_time":0.5436412917,"remaining_time":0.1970144191},
{"learn":[60.99299623],"iteration":367,"passed_time":0.5450546667,"remaining_time":0.1955087391},
{"learn":[60.97341151],"iteration":368,"passed_time":0.546597,"remaining_time":0.1940493415},
{"learn":[60.96483799],"iteration":369,"passed_time":0.547946375,"remaining_time":0.1925216993},
{"learn":[60.95315959],"iteration":370,"passed_time":0.5495135,"remaining_time":0.1910707318},
{"learn":[60.93750016],"iteration":371,"passed_time":0.5509696667,"remaining_time":0.1895809606},
{"learn":[60.91737819],"iteration":372,"passed_time":0.552463,"remaining_time":0.1881040241},
{"learn":[60.88931233],"iteration":373,"passed_time":0.5545845,"remaining_time":0.1868386283},
{"learn":[60.87193114],"iteration":374,"passed_time":0.5562333333,"remaining_time":0.1854111111},
{"learn":[60.84675725],"iteration":375,"passed_time":0.5576931667,"remaining_time":0.1839200869},
{"learn":[60.83653773],"iteration":376,"passed_time":0.55923075,"remaining_time":0.1824545948},
{"learn":[60.82063654],"iteration":377,"passed_time":0.5606986667,"remaining_time":0.1809662363},
{"learn":[60.802005],"iteration":378,"passed_time":0.5619803333,"remaining_time":0.1794185233},
{"learn":[60.79172217],"iteration":379,"passed_time":0.5632721667,"remaining_time":0.1778754211},
{"learn":[60.77033162],"iteration":380,"passed_time":0.5646663333,"remaining_time":0.1763656002},
{"learn":[60.74920188],"iteration":381,"passed_time":0.5660890417,"remaining_time":0.1748652014},
{"learn":[60.72984516],"iteration":382,"passed_time":0.5675161667,"remaining_time":0.1733665574},
{"learn":[60.70745791],"iteration":383,"passed_time":0.5690035417,"remaining_time":0.1718864865},
{"learn":[60.69623331],"iteration":384,"passed_time":0.5702856667,"remaining_time":0.1703450693},
{"learn":[60.67161445],"iteration":385,"passed_time":0.5717929167,"remaining_time":0.1688714832},
{"learn":[60.64613992],"iteration":386,"passed_time":0.5732512917,"remaining_time":0.1673834521},
{"learn":[60.63480618],"iteration":387,"passed_time":0.5746355,"remaining_time":0.1658741649},
{"learn":[60.61576641],"iteration":388,"passed_time":0.5760145833,"remaining_time":0.1643640585},
{"learn":[60.59439573],"iteration":389,"passed_time":0.577434875,"remaining_time":0.1628662468},
{"learn":[60.56642373],"iteration":390,"passed_time":0.5788425,"remaining_time":0.1613653005},
{"learn":[60.54006901],"iteration":391,"passed_time":0.5802732083,"remaining_time":0.1598711901},
{"learn":[60.51986798],"iteration":392,"passed_time":0.5817332917,"remaining_time":0.1583854},
{"learn":[60.50067678],"iteration":393,"passed_time":0.5834430417,"remaining_time":0.1569669097},
{"learn":[60.47576632],"iteration":394,"passed_time":0.5849785,"remaining_time":0.1555006139},
{"learn":[60.45877959],"iteration":395,"passed_time":0.586369125,"remaining_time":0.1539959318},
{"learn":[60.44865689],"iteration":396,"passed_time":0.5878444167,"remaining_time":0.1525137907},
{"learn":[60.43222765],"iteration":397,"passed_time":0.589224125,"remaining_time":0.1510071878},
{"learn":[60.41378084],"iteration":398,"passed_time":0.5906248333,"remaining_time":0.1495065368},
{"learn":[60.3991511],"iteration":399,"passed_time":0.5919559167,"remaining_time":0.1479889792},
{"learn":[60.38240261],"iteration":400,"passed_time":0.59327875,"remaining_time":0.1464703148},
{"learn":[60.36576803],"iteration":401,"passed_time":0.5948054167,"remaining_time":0.1450023155},
{"learn":[60.34022631],"iteration":402,"passed_time":0.59631825,"remaining_time":0.1435306954},
{"learn":[60.31531191],"iteration":403,"passed_time":0.5977995417,"remaining_time":0.1420513762},
{"learn":[60.30236176],"iteration":404,"passed_time":0.5990870417,"remaining_time":0.14052659},
{"learn":[60.27806288],"iteration":405,"passed_time":0.600447375,"remaining_time":0.1390198356},
{"learn":[60.26253778],"iteration":406,"passed_time":0.6018466667,"remaining_time":0.1375227027},
{"learn":[60.24819993],"iteration":407,"passed_time":0.6032827917,"remaining_time":0.136034355},
{"learn":[60.23024198],"iteration":408,"passed_time":0.604643375,"remaining_time":0.1345294551},
{"learn":[60.21189503],"iteration":409,"passed_time":0.6062053333,"remaining_time":0.1330694634},
{"learn":[60.18817518],"iteration":410,"passed_time":0.6077698333,"remaining_time":0.131609526},
{"learn":[60.17195832],"iteration":411,"passed_time":0.60917625,"remaining_time":0.1301153155},
{"learn":[60.1455369],"iteration":412,"passed_time":0.6105744583,"remaining_time":0.1286198012},
{"learn":[60.12328022],"iteration":413,"passed_time":0.6120717083,"remaining_time":0.1271453307},
{"learn":[60.10515079],"iteration":414,"passed_time":0.613559625,"remaining_time":0.1256688389},
{"learn":[60.08278215],"iteration":415,"passed_time":0.61492825,"remaining_time":0.1241682043},
{"learn":[60.06637236],"iteration":416,"passed_time":0.616473125,"remaining_time":0.1227032839},
{"learn":[60.0510928],"iteration":417,"passed_time":0.6178009167,"remaining_time":0.1211953951},
{"learn":[60.03217879],"iteration":418,"passed_time":0.619233625,"remaining_time":0.1197086483},
{"learn":[60.00500978],"iteration":419,"passed_time":0.6206329583,"remaining_time":0.1182158016},
{"learn":[59.98558808],"iteration":420,"passed_time":0.6221172083,"remaining_time":0.1167393336},
{"learn":[59.96269582],"iteration":421,"passed_time":0.623580375,"remaining_time":0.1152589319},
{"learn":[59.94295143],"iteration":422,"passed_time":0.6250872083,"remaining_time":0.1137865604},
{"learn":[59.92325126],"iteration":423,"passed_time":0.6265747917,"remaining_time":0.1123105759},
{"learn":[59.90546694],"iteration":424,"passed_time":0.6280139583,"remaining_time":0.1108259926},
{"learn":[59.89724706],"iteration":425,"passed_time":0.6294045,"remaining_time":0.1093331761},
{"learn":[59.87999466],"iteration":426,"passed_time":0.630943125,"remaining_time":0.1078661549},
{"learn":[59.85794733],"iteration":427,"passed_time":0.6326224583,"remaining_time":0.1064224696},
{"learn":[59.84375233],"iteration":428,"passed_time":0.6342042917,"remaining_time":0.1049615494},
{"learn":[59.82523337],"iteration":429,"passed_time":0.6356036667,"remaining_time":0.1034703643},
{"learn":[59.81338764],"iteration":430,"passed_time":0.6370634583,"remaining_time":0.1019892776},
{"learn":[59.80158092],"iteration":431,"passed_time":0.6384035833,"remaining_time":0.1004894529},
{"learn":[59.78467332],"iteration":432,"passed_time":0.639814875,"remaining_time":0.09900137789},
{"learn":[59.76127228],"iteration":433,"passed_time":0.6412872083,"remaining_time":0.09752293952},
{"learn":[59.73700607],"iteration":434,"passed_time":0.642680875,"remaining_time":0.09603277443},
{"learn":[59.71842295],"iteration":435,"passed_time":0.6441604583,"remaining_time":0.09455566361},
{"learn":[59.70623641],"iteration":436,"passed_time":0.6454859167,"remaining_time":0.09305632208},
{"learn":[59.6863106],"iteration":437,"passed_time":0.6468437917,"remaining_time":0.0915623632},
{"learn":[59.66863723],"iteration":438,"passed_time":0.6482289167,"remaining_time":0.09007281074},
{"learn":[59.65152158],"iteration":439,"passed_time":0.6500318333,"remaining_time":0.08864070455},
{"learn":[59.63066075],"iteration":440,"passed_time":0.6515368333,"remaining_time":0.08716705933},
{"learn":[59.61930002],"iteration":441,"passed_time":0.652927125,"remaining_time":0.08567822002},
{"learn":[59.59712713],"iteration":442,"passed_time":0.6544609167,"remaining_time":0.0842082895},
{"learn":[59.58013242],"iteration":443,"passed_time":0.6558788333,"remaining_time":0.08272345646},
{"learn":[59.55506421],"iteration":444,"passed_time":0.6575020417,"remaining_time":0.08126429728},
{"learn":[59.53807808],"iteration":445,"passed_time":0.6589054583,"remaining_time":0.07977779092},
{"learn":[59.52347878],"iteration":446,"passed_time":0.6603767083,"remaining_time":0.0782996992},
{"learn":[59.50923601],"iteration":447,"passed_time":0.6617658333,"remaining_time":0.07681210565},
{"learn":[59.49252555],"iteration":448,"passed_time":0.6631849583,"remaining_time":0.0753283583},
{"learn":[59.47481073],"iteration":449,"passed_time":0.664612625,"remaining_time":0.07384584722},
{"learn":[59.45792729],"iteration":450,"passed_time":0.66592775,"remaining_time":0.072351352},
{"learn":[59.43741036],"iteration":451,"passed_time":0.6673965833,"remaining_time":0.07087397345},
{"learn":[59.42165841],"iteration":452,"passed_time":0.6688054167,"remaining_time":0.06939040747},
{"learn":[59.40265698],"iteration":453,"passed_time":0.670257875,"remaining_time":0.06791159086},
{"learn":[59.38404562],"iteration":454,"passed_time":0.6716972917,"remaining_time":0.06643160027},
{"learn":[59.36545324],"iteration":455,"passed_time":0.6732499583,"remaining_time":0.06496271528},
{"learn":[59.35138233],"iteration":456,"passed_time":0.67464725,"remaining_time":0.06347884409},
{"learn":[59.32795125],"iteration":457,"passed_time":0.6761642917,"remaining_time":0.06200633242},
{"learn":[59.30880236],"iteration":458,"passed_time":0.677611375,"remaining_time":0.06052737772},
{"learn":[59.30037419],"iteration":459,"passed_time":0.678934625,"remaining_time":0.05903779348},
{"learn":[59.2790602],"iteration":460,"passed_time":0.6804294583,"remaining_time":0.05756344658},
{"learn":[59.25945102],"iteration":461,"passed_time":0.6819268333,"remaining_time":0.05608922006},
{"learn":[59.24045516],"iteration":462,"passed_time":0.6833535833,"remaining_time":0.05460924964},
{"learn":[59.23158037],"iteration":463,"passed_time":0.684703625,"remaining_time":0.05312355711},
{"learn":[59.21604647],"iteration":464,"passed_time":0.6862395833,"remaining_time":0.05165244176},
{"learn":[59.19144565],"iteration":465,"passed_time":0.687712,"remaining_time":0.05017641202},
{"learn":[59.17908291],"iteration":466,"passed_time":0.6892790833,"remaining_time":0.04870708726},
{"learn":[59.1609236],"iteration":467,"passed_time":0.6906440417,"remaining_time":0.04722352422},
{"learn":[59.14242269],"iteration":468,"passed_time":0.6920714167,"remaining_time":0.04574459257},
{"learn":[59.1218719],"iteration":469,"passed_time":0.6935572917,"remaining_time":0.04426961436},
{"learn":[59.10015086],"iteration":470,"passed_time":0.6949628333,"remaining_time":0.04278964367},
{"learn":[59.07927195],"iteration":471,"passed_time":0.6964267917,"remaining_time":0.04131345374},
{"learn":[59.05726909],"iteration":472,"passed_time":0.697858625,"remaining_time":0.03983548177},
{"learn":[59.0371874],"iteration":473,"passed_time":0.6992245417,"remaining_time":0.03835408878},
{"learn":[59.02121569],"iteration":474,"passed_time":0.7005484167,"remaining_time":0.0368709693},
{"learn":[59.00990277],"iteration":475,"passed_time":0.7019637083,"remaining_time":0.03539312815},
{"learn":[58.99104679],"iteration":476,"passed_time":0.703482375,"remaining_time":0.03392053381},
{"learn":[58.97333202],"iteration":477,"passed_time":0.7050352083,"remaining_time":0.03244931921},
{"learn":[58.95823228],"iteration":478,"passed_time":0.7064390417,"remaining_time":0.03097123147},
{"learn":[58.94654799],"iteration":479,"passed_time":0.7078092083,"remaining_time":0.02949205035},
{"learn":[58.93396031],"iteration":480,"passed_time":0.7093162083,"remaining_time":0.02801872756},
{"learn":[58.9224947],"iteration":481,"passed_time":0.71088925,"remaining_time":0.02654773133},
{"learn":[58.9051266],"iteration":482,"passed_time":0.7123702083,"remaining_time":0.02507307151},
{"learn":[58.89438492],"iteration":483,"passed_time":0.713728875,"remaining_time":0.02359434298},
{"learn":[58.87815078],"iteration":484,"passed_time":0.7152789583,"remaining_time":0.02212202964},
{"learn":[58.85953857],"iteration":485,"passed_time":0.7167898333,"remaining_time":0.0206482668},
{"learn":[58.84157577],"iteration":486,"passed_time":0.718358,"remaining_time":0.0191758809},
{"learn":[58.82993078],"iteration":487,"passed_time":0.7197137917,"remaining_time":0.01769788012},
{"learn":[58.81238628],"iteration":488,"passed_time":0.7211139167,"remaining_time":0.01622137645},
{"learn":[58.79669915],"iteration":489,"passed_time":0.7226038333,"remaining_time":0.01474701701},
{"learn":[58.78014778],"iteration":490,"passed_time":0.7239730417,"remaining_time":0.01327038162},
{"learn":[58.76033818],"iteration":491,"passed_time":0.7254833333,"remaining_time":0.01179647696},
{"learn":[58.7419974],"iteration":492,"passed_time":0.7269625417,"remaining_time":0.01032198335},
{"learn":[58.72633747],"iteration":493,"passed_time":0.7284402083,"remaining_time":0.008847451923},
{"learn":[58.71081235],"iteration":494,"passed_time":0.7299111667,"remaining_time":0.007372840067},
{"learn":[58.69962393],"iteration":495,"passed_time":0.731353375,"remaining_time":0.005898011089},
{"learn":[58.68697743],"iteration":496,"passed_time":0.7328468333,"remaining_time":0.004423622736},
{"learn":[58.67174485],"iteration":497,"passed_time":0.7342792083,"remaining_time":0.002948912483},
{"learn":[58.65797752],"iteration":498,"passed_time":0.7357115417,"remaining_time":0.001474371827},
{"learn":[58.6426804],"iteration":499,"passed_time":0.7372885833,"remaining_time":0}
]}